{
    "title": "UNGEE",
    "author": "chuxubank",
    "language": "zh-hans",
    "links": {
        "sidebar": {
            "GitHub": "https://github.com/chuxubank/UNGEE"
        }
    },
    "plugins": [
        "-lunr",
        "-search",
        "search-plus",
        "github",
        "editlink",
        "emphasize",
        "katex",
        "splitter",
        "anchor-navigation-ex",
        "expandable-chapters-interactive",
        "sitemap-general"
    ],
    "pluginsConfig": {
        "theme-default": {
            "showLevel": true
        },
        "github": {
            "url": "https://github.com/chuxubank/UNGEE"
        },
        "editlink": {
            "base": "https://github.com/chuxubank/UNGEE/edit/master/",
            "label": "编辑本页"
        },
        "anchor-navigation-ex": {
            "multipleH1": false
        },
        "sitemap-general": {
            "prefix": "https://github.com/chuxubank/UNGEE"
        }
    }
}